{
  "generated_at_utc": "2026-06-28T23:06:45+00:00",
  "source_tipsy_curve_table": "planning/tfl6_mp11_managed_curves.csv",
  "source_vdyp_curve_table": "planning/tfl6_first_growth_au_curves.csv",
  "plot_directory": "plots/mp11_tipsy_vdyp_diagnostics",
  "row_count": 27,
  "diagnostic_class_counts": {
    "tipsy_substantially_above_vdyp": 13,
    "tipsy_substantially_below_vdyp": 4,
    "tipsy_vdyp_close": 2,
    "tipsy_vdyp_moderate_difference": 8
  },
  "review_status_counts": {
    "p10r5_tipsy_vdyp_diagnostic_review_required": 27
  },
  "model_input_status_counts": {
    "not_model_input": 27
  },
  "records": [
    {
      "mp11_au_code": "FMH01",
      "mp11_feature_id": 611403,
      "mp11_tipsy_review_status": "tentatively_passed_review",
      "mp11_tipsy_comparison_class": "large_difference_review_required",
      "vdyp_au_id": "cwhvm2_hw_ba_l",
      "vdyp_natural_curve_status": "selected_curve_family_available",
      "vdyp_selected_path": "smoothed_bin_pchip",
      "vdyp_source_stand_count": 434,
      "tipsy_max_volume": 783.1,
      "vdyp_max_volume": 920.312,
      "tipsy_to_vdyp_max_ratio": 0.851,
      "tipsy_age_at_max_volume": 350,
      "vdyp_age_at_max_volume": 150,
      "tipsy_volume_age_100": 316.2,
      "vdyp_volume_age_100": 757.266,
      "tipsy_to_vdyp_age_100_ratio": 0.418,
      "common_age_rmse": 294.635,
      "common_age_mean_delta": -221.935,
      "diagnostic_class": "tipsy_substantially_below_vdyp",
      "review_status": "p10r5_tipsy_vdyp_diagnostic_review_required",
      "model_input_status": "not_model_input",
      "plot_path": "plots/mp11_tipsy_vdyp_diagnostics/mp11-fmh01_tipsy-vs-vdyp-cwhvm2-hw-ba-l.png",
      "plot_exists": true,
      "plot_size_bytes": 100586
    },
    {
      "mp11_au_code": "FMH22",
      "mp11_feature_id": 611413,
      "mp11_tipsy_review_status": "tentatively_passed_review",
      "mp11_tipsy_comparison_class": "large_difference_review_required",
      "vdyp_au_id": "cwhvm2_hw_ba_l",
      "vdyp_natural_curve_status": "selected_curve_family_available",
      "vdyp_selected_path": "smoothed_bin_pchip",
      "vdyp_source_stand_count": 434,
      "tipsy_max_volume": 769.4,
      "vdyp_max_volume": 920.312,
      "tipsy_to_vdyp_max_ratio": 0.836,
      "tipsy_age_at_max_volume": 350,
      "vdyp_age_at_max_volume": 150,
      "tipsy_volume_age_100": 282.0,
      "vdyp_volume_age_100": 757.266,
      "tipsy_to_vdyp_age_100_ratio": 0.372,
      "common_age_rmse": 317.305,
      "common_age_mean_delta": -246.732,
      "diagnostic_class": "tipsy_substantially_below_vdyp",
      "review_status": "p10r5_tipsy_vdyp_diagnostic_review_required",
      "model_input_status": "not_model_input",
      "plot_path": "plots/mp11_tipsy_vdyp_diagnostics/mp11-fmh22_tipsy-vs-vdyp-cwhvm2-hw-ba-l.png",
      "plot_exists": true,
      "plot_size_bytes": 100584
    },
    {
      "mp11_au_code": "Fvh101",
      "mp11_feature_id": 611143,
      "mp11_tipsy_review_status": "tentatively_passed_review",
      "mp11_tipsy_comparison_class": "large_difference_review_required",
      "vdyp_au_id": "cwhvh1_cw_hw_m",
      "vdyp_natural_curve_status": "selected_curve_family_available",
      "vdyp_selected_path": "smoothed_bin_pchip",
      "vdyp_source_stand_count": 118,
      "tipsy_max_volume": 767.3,
      "vdyp_max_volume": 656.797,
      "tipsy_to_vdyp_max_ratio": 1.168,
      "tipsy_age_at_max_volume": 270,
      "vdyp_age_at_max_volume": 170,
      "tipsy_volume_age_100": 464.8,
      "vdyp_volume_age_100": 480.752,
      "tipsy_to_vdyp_age_100_ratio": 0.967,
      "common_age_rmse": 101.369,
      "common_age_mean_delta": 47.297,
      "diagnostic_class": "tipsy_vdyp_moderate_difference",
      "review_status": "p10r5_tipsy_vdyp_diagnostic_review_required",
      "model_input_status": "not_model_input",
      "plot_path": "plots/mp11_tipsy_vdyp_diagnostics/mp11-fvh101_tipsy-vs-vdyp-cwhvh1-cw-hw-m.png",
      "plot_exists": true,
      "plot_size_bytes": 98790
    },
    {
      "mp11_au_code": "Fvh103",
      "mp11_feature_id": 611153,
      "mp11_tipsy_review_status": "tentatively_passed_review",
      "mp11_tipsy_comparison_class": "large_difference_review_required",
      "vdyp_au_id": "cwhvh1_cw_hw_l",
      "vdyp_natural_curve_status": "selected_curve_family_available",
      "vdyp_selected_path": "smoothed_bin_pchip",
      "vdyp_source_stand_count": 172,
      "tipsy_max_volume": 220.3,
      "vdyp_max_volume": 613.123,
      "tipsy_to_vdyp_max_ratio": 0.359,
      "tipsy_age_at_max_volume": 350,
      "vdyp_age_at_max_volume": 165,
      "tipsy_volume_age_100": 70.1,
      "vdyp_volume_age_100": 462.348,
      "tipsy_to_vdyp_age_100_ratio": 0.152,
      "common_age_rmse": 336.857,
      "common_age_mean_delta": -309.94,
      "diagnostic_class": "tipsy_substantially_below_vdyp",
      "review_status": "p10r5_tipsy_vdyp_diagnostic_review_required",
      "model_input_status": "not_model_input",
      "plot_path": "plots/mp11_tipsy_vdyp_diagnostics/mp11-fvh103_tipsy-vs-vdyp-cwhvh1-cw-hw-l.png",
      "plot_exists": true,
      "plot_size_bytes": 94335
    },
    {
      "mp11_au_code": "Fvh104",
      "mp11_feature_id": 611163,
      "mp11_tipsy_review_status": "tentatively_passed_review",
      "mp11_tipsy_comparison_class": "moderate_difference_review_required",
      "vdyp_au_id": "cwhvh1_hw_ss_m",
      "vdyp_natural_curve_status": "selected_curve_family_available",
      "vdyp_selected_path": "smoothed_bin_pchip",
      "vdyp_source_stand_count": 34,
      "tipsy_max_volume": 1278.1,
      "vdyp_max_volume": 978.448,
      "tipsy_to_vdyp_max_ratio": 1.306,
      "tipsy_age_at_max_volume": 320,
      "vdyp_age_at_max_volume": 165,
      "tipsy_volume_age_100": 792.4,
      "vdyp_volume_age_100": 741.744,
      "tipsy_to_vdyp_age_100_ratio": 1.068,
      "common_age_rmse": 250.429,
      "common_age_mean_delta": 169.274,
      "diagnostic_class": "tipsy_vdyp_moderate_difference",
      "review_status": "p10r5_tipsy_vdyp_diagnostic_review_required",
      "model_input_status": "not_model_input",
      "plot_path": "plots/mp11_tipsy_vdyp_diagnostics/mp11-fvh104_tipsy-vs-vdyp-cwhvh1-hw-ss-m.png",
      "plot_exists": true,
      "plot_size_bytes": 98979
    },
    {
      "mp11_au_code": "Fvh104s",
      "mp11_feature_id": 611173,
      "mp11_tipsy_review_status": "tentatively_passed_review",
      "mp11_tipsy_comparison_class": "moderate_difference_review_required",
      "vdyp_au_id": "cwhvh1_cw_hw_h",
      "vdyp_natural_curve_status": "selected_curve_family_available",
      "vdyp_selected_path": "smoothed_bin_pchip",
      "vdyp_source_stand_count": 138,
      "tipsy_max_volume": 1179.0,
      "vdyp_max_volume": 797.605,
      "tipsy_to_vdyp_max_ratio": 1.478,
      "tipsy_age_at_max_volume": 260,
      "vdyp_age_at_max_volume": 175,
      "tipsy_volume_age_100": 754.4,
      "vdyp_volume_age_100": 618.859,
      "tipsy_to_vdyp_age_100_ratio": 1.219,
      "common_age_rmse": 287.486,
      "common_age_mean_delta": 239.479,
      "diagnostic_class": "tipsy_substantially_above_vdyp",
      "review_status": "p10r5_tipsy_vdyp_diagnostic_review_required",
      "model_input_status": "not_model_input",
      "plot_path": "plots/mp11_tipsy_vdyp_diagnostics/mp11-fvh104s_tipsy-vs-vdyp-cwhvh1-cw-hw-h.png",
      "plot_exists": true,
      "plot_size_bytes": 96122
    },
    {
      "mp11_au_code": "Fvh106",
      "mp11_feature_id": 611183,
      "mp11_tipsy_review_status": "tentatively_passed_review",
      "mp11_tipsy_comparison_class": "moderate_difference_review_required",
      "vdyp_au_id": "cwhvh1_hw_ba_h",
      "vdyp_natural_curve_status": "selected_curve_family_available",
      "vdyp_selected_path": "smoothed_bin_pchip",
      "vdyp_source_stand_count": 57,
      "tipsy_max_volume": 1496.5,
      "vdyp_max_volume": 1069.186,
      "tipsy_to_vdyp_max_ratio": 1.4,
      "tipsy_age_at_max_volume": 260,
      "vdyp_age_at_max_volume": 165,
      "tipsy_volume_age_100": 1016.3,
      "vdyp_volume_age_100": 852.059,
      "tipsy_to_vdyp_age_100_ratio": 1.193,
      "common_age_rmse": 387.909,
      "common_age_mean_delta": 297.923,
      "diagnostic_class": "tipsy_substantially_above_vdyp",
      "review_status": "p10r5_tipsy_vdyp_diagnostic_review_required",
      "model_input_status": "not_model_input",
      "plot_path": "plots/mp11_tipsy_vdyp_diagnostics/mp11-fvh106_tipsy-vs-vdyp-cwhvh1-hw-ba-h.png",
      "plot_exists": true,
      "plot_size_bytes": 99301
    },
    {
      "mp11_au_code": "Fvh108",
      "mp11_feature_id": 611193,
      "mp11_tipsy_review_status": "tentatively_passed_review",
      "mp11_tipsy_comparison_class": "large_difference_review_required",
      "vdyp_au_id": "cwhvh1_hw_cw_h",
      "vdyp_natural_curve_status": "selected_curve_family_available",
      "vdyp_selected_path": "smoothed_bin_pchip",
      "vdyp_source_stand_count": 96,
      "tipsy_max_volume": 1305.9,
      "vdyp_max_volume": 1040.455,
      "tipsy_to_vdyp_max_ratio": 1.255,
      "tipsy_age_at_max_volume": 310,
      "vdyp_age_at_max_volume": 165,
      "tipsy_volume_age_100": 903.3,
      "vdyp_volume_age_100": 827.931,
      "tipsy_to_vdyp_age_100_ratio": 1.091,
      "common_age_rmse": 252.236,
      "common_age_mean_delta": 198.472,
      "diagnostic_class": "tipsy_vdyp_moderate_difference",
      "review_status": "p10r5_tipsy_vdyp_diagnostic_review_required",
      "model_input_status": "not_model_input",
      "plot_path": "plots/mp11_tipsy_vdyp_diagnostics/mp11-fvh108_tipsy-vs-vdyp-cwhvh1-hw-cw-h.png",
      "plot_exists": true,
      "plot_size_bytes": 98245
    },
    {
      "mp11_au_code": "Fvh113",
      "mp11_feature_id": 611203,
      "mp11_tipsy_review_status": "tentatively_passed_review",
      "mp11_tipsy_comparison_class": "large_difference_review_required",
      "vdyp_au_id": "cwhvh1_cw_hw_m",
      "vdyp_natural_curve_status": "selected_curve_family_available",
      "vdyp_selected_path": "smoothed_bin_pchip",
      "vdyp_source_stand_count": 118,
      "tipsy_max_volume": 750.0,
      "vdyp_max_volume": 656.797,
      "tipsy_to_vdyp_max_ratio": 1.142,
      "tipsy_age_at_max_volume": 270,
      "vdyp_age_at_max_volume": 170,
      "tipsy_volume_age_100": 455.7,
      "vdyp_volume_age_100": 480.752,
      "tipsy_to_vdyp_age_100_ratio": 0.948,
      "common_age_rmse": 91.89,
      "common_age_mean_delta": 35.811,
      "diagnostic_class": "tipsy_vdyp_close",
      "review_status": "p10r5_tipsy_vdyp_diagnostic_review_required",
      "model_input_status": "not_model_input",
      "plot_path": "plots/mp11_tipsy_vdyp_diagnostics/mp11-fvh113_tipsy-vs-vdyp-cwhvh1-cw-hw-m.png",
      "plot_exists": true,
      "plot_size_bytes": 96721
    },
    {
      "mp11_au_code": "Fvm101",
      "mp11_feature_id": 611213,
      "mp11_tipsy_review_status": "tentatively_passed_review",
      "mp11_tipsy_comparison_class": "moderate_difference_review_required",
      "vdyp_au_id": "cwhvm2_ba_hw_h",
      "vdyp_natural_curve_status": "selected_curve_family_available",
      "vdyp_selected_path": "smoothed_bin_pchip",
      "vdyp_source_stand_count": 36,
      "tipsy_max_volume": 1541.7,
      "vdyp_max_volume": 1197.499,
      "tipsy_to_vdyp_max_ratio": 1.287,
      "tipsy_age_at_max_volume": 320,
      "vdyp_age_at_max_volume": 170,
      "tipsy_volume_age_100": 1067.9,
      "vdyp_volume_age_100": 976.344,
      "tipsy_to_vdyp_age_100_ratio": 1.094,
      "common_age_rmse": 233.398,
      "common_age_mean_delta": 184.626,
      "diagnostic_class": "tipsy_vdyp_moderate_difference",
      "review_status": "p10r5_tipsy_vdyp_diagnostic_review_required",
      "model_input_status": "not_model_input",
      "plot_path": "plots/mp11_tipsy_vdyp_diagnostics/mp11-fvm101_tipsy-vs-vdyp-cwhvm2-ba-hw-h.png",
      "plot_exists": true,
      "plot_size_bytes": 96483
    },
    {
      "mp11_au_code": "Fvm101s",
      "mp11_feature_id": 611223,
      "mp11_tipsy_review_status": "tentatively_passed_review",
      "mp11_tipsy_comparison_class": "large_difference_review_required",
      "vdyp_au_id": "cwhvm1_cw_hw_h",
      "vdyp_natural_curve_status": "selected_curve_family_available",
      "vdyp_selected_path": "smoothed_bin_pchip",
      "vdyp_source_stand_count": 694,
      "tipsy_max_volume": 1429.6,
      "vdyp_max_volume": 943.689,
      "tipsy_to_vdyp_max_ratio": 1.515,
      "tipsy_age_at_max_volume": 260,
      "vdyp_age_at_max_volume": 170,
      "tipsy_volume_age_100": 967.8,
      "vdyp_volume_age_100": 739.508,
      "tipsy_to_vdyp_age_100_ratio": 1.309,
      "common_age_rmse": 367.948,
      "common_age_mean_delta": 316.915,
      "diagnostic_class": "tipsy_substantially_above_vdyp",
      "review_status": "p10r5_tipsy_vdyp_diagnostic_review_required",
      "model_input_status": "not_model_input",
      "plot_path": "plots/mp11_tipsy_vdyp_diagnostics/mp11-fvm101s_tipsy-vs-vdyp-cwhvm1-cw-hw-h.png",
      "plot_exists": true,
      "plot_size_bytes": 97139
    },
    {
      "mp11_au_code": "Fvm103",
      "mp11_feature_id": 611233,
      "mp11_tipsy_review_status": "tentatively_passed_review",
      "mp11_tipsy_comparison_class": "large_difference_review_required",
      "vdyp_au_id": "cwhvm2_yc_hw_h",
      "vdyp_natural_curve_status": "selected_curve_family_available",
      "vdyp_selected_path": "smoothed_bin_pchip",
      "vdyp_source_stand_count": 33,
      "tipsy_max_volume": 922.0,
      "vdyp_max_volume": 832.912,
      "tipsy_to_vdyp_max_ratio": 1.107,
      "tipsy_age_at_max_volume": 270,
      "vdyp_age_at_max_volume": 180,
      "tipsy_volume_age_100": 601.0,
      "vdyp_volume_age_100": 662.802,
      "tipsy_to_vdyp_age_100_ratio": 0.907,
      "common_age_rmse": 88.501,
      "common_age_mean_delta": 29.189,
      "diagnostic_class": "tipsy_vdyp_close",
      "review_status": "p10r5_tipsy_vdyp_diagnostic_review_required",
      "model_input_status": "not_model_input",
      "plot_path": "plots/mp11_tipsy_vdyp_diagnostics/mp11-fvm103_tipsy-vs-vdyp-cwhvm2-yc-hw-h.png",
      "plot_exists": true,
      "plot_size_bytes": 94733
    },
    {
      "mp11_au_code": "Fvm104",
      "mp11_feature_id": 611243,
      "mp11_tipsy_review_status": "tentatively_passed_review",
      "mp11_tipsy_comparison_class": "moderate_difference_review_required",
      "vdyp_au_id": "cwhvm1_ss_hw_l",
      "vdyp_natural_curve_status": "selected_curve_family_available",
      "vdyp_selected_path": "smoothed_bin_pchip",
      "vdyp_source_stand_count": 49,
      "tipsy_max_volume": 1621.4,
      "vdyp_max_volume": 1099.624,
      "tipsy_to_vdyp_max_ratio": 1.475,
      "tipsy_age_at_max_volume": 350,
      "vdyp_age_at_max_volume": 175,
      "tipsy_volume_age_100": 959.0,
      "vdyp_volume_age_100": 877.908,
      "tipsy_to_vdyp_age_100_ratio": 1.092,
      "common_age_rmse": 323.892,
      "common_age_mean_delta": 237.675,
      "diagnostic_class": "tipsy_substantially_above_vdyp",
      "review_status": "p10r5_tipsy_vdyp_diagnostic_review_required",
      "model_input_status": "not_model_input",
      "plot_path": "plots/mp11_tipsy_vdyp_diagnostics/mp11-fvm104_tipsy-vs-vdyp-cwhvm1-ss-hw-l.png",
      "plot_exists": true,
      "plot_size_bytes": 98574
    },
    {
      "mp11_au_code": "Fvm105",
      "mp11_feature_id": 611253,
      "mp11_tipsy_review_status": "tentatively_passed_review",
      "mp11_tipsy_comparison_class": "moderate_difference_review_required",
      "vdyp_au_id": "cwhvm1_hw_ss_m",
      "vdyp_natural_curve_status": "selected_curve_family_available",
      "vdyp_selected_path": "smoothed_bin_pchip",
      "vdyp_source_stand_count": 72,
      "tipsy_max_volume": 1494.9,
      "vdyp_max_volume": 1193.284,
      "tipsy_to_vdyp_max_ratio": 1.253,
      "tipsy_age_at_max_volume": 250,
      "vdyp_age_at_max_volume": 175,
      "tipsy_volume_age_100": 1141.0,
      "vdyp_volume_age_100": 954.19,
      "tipsy_to_vdyp_age_100_ratio": 1.196,
      "common_age_rmse": 253.463,
      "common_age_mean_delta": 220.895,
      "diagnostic_class": "tipsy_vdyp_moderate_difference",
      "review_status": "p10r5_tipsy_vdyp_diagnostic_review_required",
      "model_input_status": "not_model_input",
      "plot_path": "plots/mp11_tipsy_vdyp_diagnostics/mp11-fvm105_tipsy-vs-vdyp-cwhvm1-hw-ss-m.png",
      "plot_exists": true,
      "plot_size_bytes": 97875
    },
    {
      "mp11_au_code": "Fvm106",
      "mp11_feature_id": 611263,
      "mp11_tipsy_review_status": "tentatively_passed_review",
      "mp11_tipsy_comparison_class": "moderate_difference_review_required",
      "vdyp_au_id": "cwhvm1_hw_ss_l",
      "vdyp_natural_curve_status": "selected_curve_family_available",
      "vdyp_selected_path": "smoothed_bin_pchip",
      "vdyp_source_stand_count": 449,
      "tipsy_max_volume": 1529.8,
      "vdyp_max_volume": 1057.283,
      "tipsy_to_vdyp_max_ratio": 1.447,
      "tipsy_age_at_max_volume": 310,
      "vdyp_age_at_max_volume": 175,
      "tipsy_volume_age_100": 973.8,
      "vdyp_volume_age_100": 821.624,
      "tipsy_to_vdyp_age_100_ratio": 1.185,
      "common_age_rmse": 335.933,
      "common_age_mean_delta": 262.318,
      "diagnostic_class": "tipsy_substantially_above_vdyp",
      "review_status": "p10r5_tipsy_vdyp_diagnostic_review_required",
      "model_input_status": "not_model_input",
      "plot_path": "plots/mp11_tipsy_vdyp_diagnostics/mp11-fvm106_tipsy-vs-vdyp-cwhvm1-hw-ss-l.png",
      "plot_exists": true,
      "plot_size_bytes": 98938
    },
    {
      "mp11_au_code": "Fvm106s",
      "mp11_feature_id": 611273,
      "mp11_tipsy_review_status": "tentatively_passed_review",
      "mp11_tipsy_comparison_class": "large_difference_review_required",
      "vdyp_au_id": "cwhvm1_cw_hw_h",
      "vdyp_natural_curve_status": "selected_curve_family_available",
      "vdyp_selected_path": "smoothed_bin_pchip",
      "vdyp_source_stand_count": 694,
      "tipsy_max_volume": 1462.2,
      "vdyp_max_volume": 943.689,
      "tipsy_to_vdyp_max_ratio": 1.549,
      "tipsy_age_at_max_volume": 260,
      "vdyp_age_at_max_volume": 170,
      "tipsy_volume_age_100": 992.3,
      "vdyp_volume_age_100": 739.508,
      "tipsy_to_vdyp_age_100_ratio": 1.342,
      "common_age_rmse": 395.184,
      "common_age_mean_delta": 342.515,
      "diagnostic_class": "tipsy_substantially_above_vdyp",
      "review_status": "p10r5_tipsy_vdyp_diagnostic_review_required",
      "model_input_status": "not_model_input",
      "plot_path": "plots/mp11_tipsy_vdyp_diagnostics/mp11-fvm106s_tipsy-vs-vdyp-cwhvm1-cw-hw-h.png",
      "plot_exists": true,
      "plot_size_bytes": 98116
    },
    {
      "mp11_au_code": "Fvm107",
      "mp11_feature_id": 611283,
      "mp11_tipsy_review_status": "tentatively_passed_review",
      "mp11_tipsy_comparison_class": "moderate_difference_review_required",
      "vdyp_au_id": "cwhvm1_hw_cw_h",
      "vdyp_natural_curve_status": "selected_curve_family_available",
      "vdyp_selected_path": "smoothed_bin_pchip",
      "vdyp_source_stand_count": 342,
      "tipsy_max_volume": 1645.4,
      "vdyp_max_volume": 1191.464,
      "tipsy_to_vdyp_max_ratio": 1.381,
      "tipsy_age_at_max_volume": 230,
      "vdyp_age_at_max_volume": 170,
      "tipsy_volume_age_100": 1198.6,
      "vdyp_volume_age_100": 949.431,
      "tipsy_to_vdyp_age_100_ratio": 1.262,
      "common_age_rmse": 353.175,
      "common_age_mean_delta": 311.755,
      "diagnostic_class": "tipsy_substantially_above_vdyp",
      "review_status": "p10r5_tipsy_vdyp_diagnostic_review_required",
      "model_input_status": "not_model_input",
      "plot_path": "plots/mp11_tipsy_vdyp_diagnostics/mp11-fvm107_tipsy-vs-vdyp-cwhvm1-hw-cw-h.png",
      "plot_exists": true,
      "plot_size_bytes": 100093
    },
    {
      "mp11_au_code": "Fvm109",
      "mp11_feature_id": 611293,
      "mp11_tipsy_review_status": "tentatively_passed_review",
      "mp11_tipsy_comparison_class": "moderate_difference_review_required",
      "vdyp_au_id": "cwhvm1_hw_fdc_l",
      "vdyp_natural_curve_status": "selected_curve_family_available",
      "vdyp_selected_path": "smoothed_bin_pchip",
      "vdyp_source_stand_count": 108,
      "tipsy_max_volume": 1560.2,
      "vdyp_max_volume": 1153.231,
      "tipsy_to_vdyp_max_ratio": 1.353,
      "tipsy_age_at_max_volume": 330,
      "vdyp_age_at_max_volume": 170,
      "tipsy_volume_age_100": 1045.9,
      "vdyp_volume_age_100": 901.54,
      "tipsy_to_vdyp_age_100_ratio": 1.16,
      "common_age_rmse": 288.659,
      "common_age_mean_delta": 233.772,
      "diagnostic_class": "tipsy_substantially_above_vdyp",
      "review_status": "p10r5_tipsy_vdyp_diagnostic_review_required",
      "model_input_status": "not_model_input",
      "plot_path": "plots/mp11_tipsy_vdyp_diagnostics/mp11-fvm109_tipsy-vs-vdyp-cwhvm1-hw-fdc-l.png",
      "plot_exists": true,
      "plot_size_bytes": 98622
    },
    {
      "mp11_au_code": "Fvm111",
      "mp11_feature_id": 611303,
      "mp11_tipsy_review_status": "tentatively_passed_review",
      "mp11_tipsy_comparison_class": "moderate_difference_review_required",
      "vdyp_au_id": "cwhvm1_hw_ss_m",
      "vdyp_natural_curve_status": "selected_curve_family_available",
      "vdyp_selected_path": "smoothed_bin_pchip",
      "vdyp_source_stand_count": 72,
      "tipsy_max_volume": 1658.5,
      "vdyp_max_volume": 1193.284,
      "tipsy_to_vdyp_max_ratio": 1.39,
      "tipsy_age_at_max_volume": 280,
      "vdyp_age_at_max_volume": 175,
      "tipsy_volume_age_100": 1200.4,
      "vdyp_volume_age_100": 954.19,
      "tipsy_to_vdyp_age_100_ratio": 1.258,
      "common_age_rmse": 349.988,
      "common_age_mean_delta": 303.34,
      "diagnostic_class": "tipsy_substantially_above_vdyp",
      "review_status": "p10r5_tipsy_vdyp_diagnostic_review_required",
      "model_input_status": "not_model_input",
      "plot_path": "plots/mp11_tipsy_vdyp_diagnostics/mp11-fvm111_tipsy-vs-vdyp-cwhvm1-hw-ss-m.png",
      "plot_exists": true,
      "plot_size_bytes": 98866
    },
    {
      "mp11_au_code": "Fvm114",
      "mp11_feature_id": 611313,
      "mp11_tipsy_review_status": "tentatively_passed_review",
      "mp11_tipsy_comparison_class": "moderate_difference_review_required",
      "vdyp_au_id": "cwhvm2_yc_hw_h",
      "vdyp_natural_curve_status": "selected_curve_family_available",
      "vdyp_selected_path": "smoothed_bin_pchip",
      "vdyp_source_stand_count": 33,
      "tipsy_max_volume": 1095.4,
      "vdyp_max_volume": 832.912,
      "tipsy_to_vdyp_max_ratio": 1.315,
      "tipsy_age_at_max_volume": 260,
      "vdyp_age_at_max_volume": 180,
      "tipsy_volume_age_100": 708.2,
      "vdyp_volume_age_100": 662.802,
      "tipsy_to_vdyp_age_100_ratio": 1.068,
      "common_age_rmse": 201.979,
      "common_age_mean_delta": 149.979,
      "diagnostic_class": "tipsy_vdyp_moderate_difference",
      "review_status": "p10r5_tipsy_vdyp_diagnostic_review_required",
      "model_input_status": "not_model_input",
      "plot_path": "plots/mp11_tipsy_vdyp_diagnostics/mp11-fvm114_tipsy-vs-vdyp-cwhvm2-yc-hw-h.png",
      "plot_exists": true,
      "plot_size_bytes": 95042
    },
    {
      "mp11_au_code": "Fvm131",
      "mp11_feature_id": 611323,
      "mp11_tipsy_review_status": "tentatively_passed_review",
      "mp11_tipsy_comparison_class": "large_difference_review_required",
      "vdyp_au_id": "cwhvm1_hw_dr_l",
      "vdyp_natural_curve_status": "selected_curve_family_available",
      "vdyp_selected_path": "smoothed_bin_pchip",
      "vdyp_source_stand_count": 147,
      "tipsy_max_volume": 1044.5,
      "vdyp_max_volume": 740.151,
      "tipsy_to_vdyp_max_ratio": 1.411,
      "tipsy_age_at_max_volume": 260,
      "vdyp_age_at_max_volume": 155,
      "tipsy_volume_age_100": 658.8,
      "vdyp_volume_age_100": 611.498,
      "tipsy_to_vdyp_age_100_ratio": 1.077,
      "common_age_rmse": 265.282,
      "common_age_mean_delta": 197.163,
      "diagnostic_class": "tipsy_substantially_above_vdyp",
      "review_status": "p10r5_tipsy_vdyp_diagnostic_review_required",
      "model_input_status": "not_model_input",
      "plot_path": "plots/mp11_tipsy_vdyp_diagnostics/mp11-fvm131_tipsy-vs-vdyp-cwhvm1-hw-dr-l.png",
      "plot_exists": true,
      "plot_size_bytes": 92587
    },
    {
      "mp11_au_code": "Fvm133",
      "mp11_feature_id": 611333,
      "mp11_tipsy_review_status": "tentatively_passed_review",
      "mp11_tipsy_comparison_class": "low_difference",
      "vdyp_au_id": "cwhvm1_cw_hw_m",
      "vdyp_natural_curve_status": "selected_curve_family_available",
      "vdyp_selected_path": "smoothed_bin_pchip",
      "vdyp_source_stand_count": 544,
      "tipsy_max_volume": 986.5,
      "vdyp_max_volume": 830.562,
      "tipsy_to_vdyp_max_ratio": 1.188,
      "tipsy_age_at_max_volume": 250,
      "vdyp_age_at_max_volume": 165,
      "tipsy_volume_age_100": 645.7,
      "vdyp_volume_age_100": 648.166,
      "tipsy_to_vdyp_age_100_ratio": 0.996,
      "common_age_rmse": 136.572,
      "common_age_mean_delta": 89.841,
      "diagnostic_class": "tipsy_vdyp_moderate_difference",
      "review_status": "p10r5_tipsy_vdyp_diagnostic_review_required",
      "model_input_status": "not_model_input",
      "plot_path": "plots/mp11_tipsy_vdyp_diagnostics/mp11-fvm133_tipsy-vs-vdyp-cwhvm1-cw-hw-m.png",
      "plot_exists": true,
      "plot_size_bytes": 95807
    },
    {
      "mp11_au_code": "Fvm201",
      "mp11_feature_id": 611343,
      "mp11_tipsy_review_status": "tentatively_passed_review",
      "mp11_tipsy_comparison_class": "large_difference_review_required",
      "vdyp_au_id": "cwhvm1_cw_hw_h",
      "vdyp_natural_curve_status": "selected_curve_family_available",
      "vdyp_selected_path": "smoothed_bin_pchip",
      "vdyp_source_stand_count": 694,
      "tipsy_max_volume": 1459.3,
      "vdyp_max_volume": 943.689,
      "tipsy_to_vdyp_max_ratio": 1.546,
      "tipsy_age_at_max_volume": 350,
      "vdyp_age_at_max_volume": 170,
      "tipsy_volume_age_100": 876.5,
      "vdyp_volume_age_100": 739.508,
      "tipsy_to_vdyp_age_100_ratio": 1.185,
      "common_age_rmse": 323.779,
      "common_age_mean_delta": 264.246,
      "diagnostic_class": "tipsy_substantially_above_vdyp",
      "review_status": "p10r5_tipsy_vdyp_diagnostic_review_required",
      "model_input_status": "not_model_input",
      "plot_path": "plots/mp11_tipsy_vdyp_diagnostics/mp11-fvm201_tipsy-vs-vdyp-cwhvm1-cw-hw-h.png",
      "plot_exists": true,
      "plot_size_bytes": 97301
    },
    {
      "mp11_au_code": "Fvm203",
      "mp11_feature_id": 611353,
      "mp11_tipsy_review_status": "tentatively_passed_review",
      "mp11_tipsy_comparison_class": "large_difference_review_required",
      "vdyp_au_id": "cwhvm2_cw_hw_m",
      "vdyp_natural_curve_status": "selected_curve_family_available",
      "vdyp_selected_path": "smoothed_bin_pchip",
      "vdyp_source_stand_count": 44,
      "tipsy_max_volume": 827.6,
      "vdyp_max_volume": 696.38,
      "tipsy_to_vdyp_max_ratio": 1.188,
      "tipsy_age_at_max_volume": 350,
      "vdyp_age_at_max_volume": 165,
      "tipsy_volume_age_100": 403.1,
      "vdyp_volume_age_100": 496.435,
      "tipsy_to_vdyp_age_100_ratio": 0.812,
      "common_age_rmse": 136.396,
      "common_age_mean_delta": 32.568,
      "diagnostic_class": "tipsy_vdyp_moderate_difference",
      "review_status": "p10r5_tipsy_vdyp_diagnostic_review_required",
      "model_input_status": "not_model_input",
      "plot_path": "plots/mp11_tipsy_vdyp_diagnostics/mp11-fvm203_tipsy-vs-vdyp-cwhvm2-cw-hw-m.png",
      "plot_exists": true,
      "plot_size_bytes": 105431
    },
    {
      "mp11_au_code": "Fvm207",
      "mp11_feature_id": 611373,
      "mp11_tipsy_review_status": "tentatively_passed_review",
      "mp11_tipsy_comparison_class": "low_difference",
      "vdyp_au_id": "cwhvm1_hw_cw_m",
      "vdyp_natural_curve_status": "selected_curve_family_available",
      "vdyp_selected_path": "smoothed_bin_pchip",
      "vdyp_source_stand_count": 1562,
      "tipsy_max_volume": 1707.4,
      "vdyp_max_volume": 1049.39,
      "tipsy_to_vdyp_max_ratio": 1.627,
      "tipsy_age_at_max_volume": 330,
      "vdyp_age_at_max_volume": 175,
      "tipsy_volume_age_100": 1052.4,
      "vdyp_volume_age_100": 813.825,
      "tipsy_to_vdyp_age_100_ratio": 1.293,
      "common_age_rmse": 434.432,
      "common_age_mean_delta": 363.001,
      "diagnostic_class": "tipsy_substantially_above_vdyp",
      "review_status": "p10r5_tipsy_vdyp_diagnostic_review_required",
      "model_input_status": "not_model_input",
      "plot_path": "plots/mp11_tipsy_vdyp_diagnostics/mp11-fvm207_tipsy-vs-vdyp-cwhvm1-hw-cw-m.png",
      "plot_exists": true,
      "plot_size_bytes": 99573
    },
    {
      "mp11_au_code": "Fvm208",
      "mp11_feature_id": 611383,
      "mp11_tipsy_review_status": "tentatively_passed_review",
      "mp11_tipsy_comparison_class": "low_difference",
      "vdyp_au_id": "cwhvm1_hw_cw_m",
      "vdyp_natural_curve_status": "selected_curve_family_available",
      "vdyp_selected_path": "smoothed_bin_pchip",
      "vdyp_source_stand_count": 1562,
      "tipsy_max_volume": 1707.4,
      "vdyp_max_volume": 1049.39,
      "tipsy_to_vdyp_max_ratio": 1.627,
      "tipsy_age_at_max_volume": 330,
      "vdyp_age_at_max_volume": 175,
      "tipsy_volume_age_100": 1052.4,
      "vdyp_volume_age_100": 813.825,
      "tipsy_to_vdyp_age_100_ratio": 1.293,
      "common_age_rmse": 434.432,
      "common_age_mean_delta": 363.001,
      "diagnostic_class": "tipsy_substantially_above_vdyp",
      "review_status": "p10r5_tipsy_vdyp_diagnostic_review_required",
      "model_input_status": "not_model_input",
      "plot_path": "plots/mp11_tipsy_vdyp_diagnostics/mp11-fvm208_tipsy-vs-vdyp-cwhvm1-hw-cw-m.png",
      "plot_exists": true,
      "plot_size_bytes": 100166
    },
    {
      "mp11_au_code": "Fvm211",
      "mp11_feature_id": 611393,
      "mp11_tipsy_review_status": "tentatively_passed_review",
      "mp11_tipsy_comparison_class": "large_difference_review_required",
      "vdyp_au_id": "cwhvm1_hw_cw_l",
      "vdyp_natural_curve_status": "selected_curve_family_available",
      "vdyp_selected_path": "smoothed_bin_pchip",
      "vdyp_source_stand_count": 1059,
      "tipsy_max_volume": 830.4,
      "vdyp_max_volume": 833.555,
      "tipsy_to_vdyp_max_ratio": 0.996,
      "tipsy_age_at_max_volume": 350,
      "vdyp_age_at_max_volume": 170,
      "tipsy_volume_age_100": 412.5,
      "vdyp_volume_age_100": 635.868,
      "tipsy_to_vdyp_age_100_ratio": 0.649,
      "common_age_rmse": 148.808,
      "common_age_mean_delta": -90.761,
      "diagnostic_class": "tipsy_substantially_below_vdyp",
      "review_status": "p10r5_tipsy_vdyp_diagnostic_review_required",
      "model_input_status": "not_model_input",
      "plot_path": "plots/mp11_tipsy_vdyp_diagnostics/mp11-fvm211_tipsy-vs-vdyp-cwhvm1-hw-cw-l.png",
      "plot_exists": true,
      "plot_size_bytes": 104040
    }
  ]
}
